{
  "definitions": {},
  "info": {
    "description": "Specification JSONs: [v2](/api-spec/v2), [v3](/api-spec/v3)."
  },
  "paths": {
    "/testApi/hello": {
      "post": {
        "summary": "/testApi/hello",
        "consumes": [
          "application/json"
        ],
        "parameters": [
          {
            "in": "body",
            "name": "body",
            "required": true,
            "schema": {
              "type": "object",
              "properties": {
                "name": {
                  "type": "string",
                  "example": "Ben"
                }
              }
            }
          }
        ],
        "responses": {
          "200": {
            "description": "OK",
            "schema": {
              "type": "object",
              "properties": {
                "msg": {
                  "type": "string",
                  "example": "Hello Ben!"
                }
              }
            }
          }
        },
        "tags": [],
        "produces": [
          "application/json"
        ]
      }
    }
  },
  "swagger": "2.0",
  "tags": [],
  "schemes": [
    "http"
  ],
  "host": "127.0.0.1:42847"
}